beautifulemail/__init__.py
beautifulemail/base.py
beautifulemail/templates/msft_plain_blue.html
beautifulemail-0.1.2.dist-info/LICENSE
beautifulemail-0.1.2.dist-info/METADATA
beautifulemail-0.1.2.dist-info/WHEEL
beautifulemail-0.1.2.dist-info/top_level.txt
beautifulemail-0.1.2.dist-info/RECORD
