Metadata-Version: 2.1
Name: beautifulemail
Version: 0.1.2
Summary: BeautifulEmail is a python package that makes it easy and quick to save pandas dataframes in beautifully formatted excel files. BeautifulEmail is the Openpyxl for Data Scientists with a deadline.
Home-page: https://github.com/vanalmsick/beautifulemail
Author: https://github.com/vanalmsick
Project-URL: Issues, https://github.com/vanalmsick/beautifulemail/issues
Project-URL: Documentation, https://vanalmsick.github.io/beautifulemail/
Project-URL: Source Code, https://github.com/vanalmsick/beautifulemail
Classifier: Programming Language :: Python :: 3
Classifier: License :: OSI Approved :: MIT License
Classifier: Operating System :: OS Independent
Requires-Python: >=3.7
License-File: LICENSE
Requires-Dist: markdown2
Requires-Dist: datetime
Requires-Dist: numpy
Requires-Dist: pandas
Requires-Dist: libsass
Requires-Dist: beautifulsoup4
